ukbaccessrepo/__init__.py
ukbaccessrepo/module_bulk_data_handler.py
ukbaccessrepo/module_genetic_data_handler.py
ukbaccessrepo/module_harmonize_fs_data.py
ukbaccessrepo/module_scalar_data_handler.py
ukbaccessrepo/temp.py
ukbaccessrepo-0.370.dist-info/LICENSE
ukbaccessrepo-0.370.dist-info/METADATA
ukbaccessrepo-0.370.dist-info/WHEEL
ukbaccessrepo-0.370.dist-info/top_level.txt
ukbaccessrepo-0.370.dist-info/RECORD
