Metadata-Version: 2.1
Name: ukbaccessrepo
Version: 0.370
Summary: UKB Access Repo
Home-page: UNKNOWN
Author: Tigmanshu Chaudhary
License: UNKNOWN
Platform: UNKNOWN
Classifier: Programming Language :: Python :: 3
Classifier: License :: OSI Approved :: MIT License
Classifier: Operating System :: OS Independent
Requires-Python: >=3.6
License-File: LICENSE
Requires-Dist: pandas
Requires-Dist: datalad
Requires-Dist: pandas-plink
Requires-Dist: numpy
Requires-Dist: dataclasses
